connectrum/__init__.py
connectrum/client.py
connectrum/constants.py
connectrum/exc.py
connectrum/findall.py
connectrum/protocol.py
connectrum/servers.json
connectrum/svr_info.py
connectrum/utils.py
connectrum-0.5.0.dist-info/DESCRIPTION.rst
connectrum-0.5.0.dist-info/METADATA
connectrum-0.5.0.dist-info/RECORD
connectrum-0.5.0.dist-info/WHEEL
connectrum-0.5.0.dist-info/metadata.json
connectrum-0.5.0.dist-info/top_level.txt
