Metadata-Version: 2.0
Name: connectrum
Version: 0.5.0
Summary: asyncio-based Electrum client library
Home-page: https://github.com/coinkite/connectrum
Author: Peter Gray
Author-email: peter@coinkite.com
License: MIT
Keywords: electrum bitcoin asnycio client
Platform: any
Classifier: Development Status :: 4 - Beta
Classifier: Intended Audience :: Developers
Classifier: License :: OSI Approved :: MIT License
Classifier: Operating System :: OS Independent
Classifier: Programming Language :: Python
Classifier: Programming Language :: Python :: 3
Classifier: Programming Language :: Python :: 3.5
Classifier: Topic :: Software Development :: Libraries
Requires-Dist: aiosocks
Requires-Dist: bottom (>=1.0.2)
